arxiv_rename/__init__.py
arxiv_rename/__main__.py
arxiv_rename/arxiv_detect.py
arxiv_rename/arxiv_rename.py
arxiv_rename/arxiv_watcher.py
arxiv_rename-0.0.4.dist-info/LICENSE.md
arxiv_rename-0.0.4.dist-info/METADATA
arxiv_rename-0.0.4.dist-info/WHEEL
arxiv_rename-0.0.4.dist-info/top_level.txt
arxiv_rename-0.0.4.dist-info/RECORD
